<?xml version="1.0" encoding="UTF-8"?>
<objects serializationModel="Studio.02.02.00">
	<object class="Event" id="{d7fe7dc7-e791-4394-b624-5f2f1cd0c4dc}">
		<property name="name">
			<value>laprankgoldland</value>
		</property>
		<property name="outputFormat">
			<value>1</value>
		</property>
		<relationship name="folder">
			<destination>{cdfd3fd9-90ae-42bf-a2a3-fc7ecd413433}</destination>
		</relationship>
		<relationship name="mixer">
			<destination>{90a0fd09-2c38-4f67-8860-98d67e461fd1}</destination>
		</relationship>
		<relationship name="masterTrack">
			<destination>{0350d234-855d-46b5-8d97-694d2608c7a6}</destination>
		</relationship>
		<relationship name="mixerInput">
			<destination>{9096ca9a-c2f8-4b99-8ee2-6d60b39a9963}</destination>
		</relationship>
		<relationship name="automatableProperties">
			<destination>{f76e936a-745b-4b94-adad-dc53e8395975}</destination>
		</relationship>
		<relationship name="markerTracks">
			<destination>{855a1a2c-0e47-4f38-8d70-2d281ab9bf24}</destination>
		</relationship>
		<relationship name="groupTracks">
			<destination>{63b0dbaf-5270-4a65-b2b5-87d8799a1745}</destination>
		</relationship>
		<relationship name="timeline">
			<destination>{fefaf801-91c5-41e7-9e63-a36cb99b4a21}</destination>
		</relationship>
		<relationship name="banks">
			<destination>{17d7dc1e-68b6-4c93-9466-72b6197503a7}</destination>
		</relationship>
	</object>
	<object class="EventMixer" id="{90a0fd09-2c38-4f67-8860-98d67e461fd1}">
		<relationship name="masterBus">
			<destination>{33d57083-3883-43c2-a54f-2708bb9238d3}</destination>
		</relationship>
	</object>
	<object class="MasterTrack" id="{0350d234-855d-46b5-8d97-694d2608c7a6}">
		<relationship name="mixerGroup">
			<destination>{33d57083-3883-43c2-a54f-2708bb9238d3}</destination>
		</relationship>
	</object>
	<object class="MixerInput" id="{9096ca9a-c2f8-4b99-8ee2-6d60b39a9963}">
		<relationship name="effectChain">
			<destination>{64314c03-d9c4-49d3-a090-6339c7c7457c}</destination>
		</relationship>
		<relationship name="panner">
			<destination>{c68b8553-92ef-43b8-88ce-a3b0bc9e303e}</destination>
		</relationship>
		<relationship name="output">
			<destination>{8ca145ee-c77d-4478-9af9-3941e6ee6b0a}</destination>
		</relationship>
	</object>
	<object class="EventAutomatableProperties" id="{f76e936a-745b-4b94-adad-dc53e8395975}">
		<property name="dopplerScale">
			<value>0</value>
		</property>
		<property name="minimumDistance">
			<value>0</value>
		</property>
		<property name="maximumDistance">
			<value>2000</value>
		</property>
	</object>
	<object class="MarkerTrack" id="{855a1a2c-0e47-4f38-8d70-2d281ab9bf24}" />
	<object class="GroupTrack" id="{63b0dbaf-5270-4a65-b2b5-87d8799a1745}">
		<relationship name="modules">
			<destination>{e09a4ab9-8364-4f25-9e89-526bc9afb05f}</destination>
		</relationship>
		<relationship name="mixerGroup">
			<destination>{d7dd9972-d2b8-4f61-87e1-fab33855412a}</destination>
		</relationship>
	</object>
	<object class="Timeline" id="{fefaf801-91c5-41e7-9e63-a36cb99b4a21}">
		<relationship name="modules">
			<destination>{e09a4ab9-8364-4f25-9e89-526bc9afb05f}</destination>
		</relationship>
	</object>
	<object class="EventMixerMaster" id="{33d57083-3883-43c2-a54f-2708bb9238d3}">
		<relationship name="effectChain">
			<destination>{556d7ca2-8197-4637-a1ef-788c3ea87015}</destination>
		</relationship>
		<relationship name="panner">
			<destination>{f4feae7f-d077-4753-8463-8c35b537c117}</destination>
		</relationship>
		<relationship name="mixer">
			<destination>{90a0fd09-2c38-4f67-8860-98d67e461fd1}</destination>
		</relationship>
	</object>
	<object class="MixerBusEffectChain" id="{64314c03-d9c4-49d3-a090-6339c7c7457c}">
		<relationship name="effects">
			<destination>{5c9de8bd-c40a-464d-8532-057ea68b2e7e}</destination>
		</relationship>
	</object>
	<object class="MixerBusPanner" id="{c68b8553-92ef-43b8-88ce-a3b0bc9e303e}" />
	<object class="SingleSound" id="{e09a4ab9-8364-4f25-9e89-526bc9afb05f}">
		<property name="length">
			<value>1.9446822514709907</value>
		</property>
		<property name="timelockedOffset">
			<value>0.27238459669582116</value>
		</property>
		<property name="volume">
			<value>5.5</value>
		</property>
		<relationship name="fadeInCurve">
			<destination>{30ff5622-3741-4763-a787-1d63c314b251}</destination>
		</relationship>
		<relationship name="fadeOutCurve">
			<destination>{66da9113-c40e-4b89-b959-094559fa544c}</destination>
		</relationship>
		<relationship name="audioFile">
			<destination>{4f20d159-3288-4ceb-8f6b-93a0b7bc0f9c}</destination>
		</relationship>
	</object>
	<object class="EventMixerGroup" id="{d7dd9972-d2b8-4f61-87e1-fab33855412a}">
		<property name="name">
			<value>Audio 2</value>
		</property>
		<relationship name="effectChain">
			<destination>{c12fd2bd-02e0-409e-b60c-d6c1a3901557}</destination>
		</relationship>
		<relationship name="panner">
			<destination>{ec452c76-ce2e-4700-a924-d551c3681a2e}</destination>
		</relationship>
		<relationship name="output">
			<destination>{33d57083-3883-43c2-a54f-2708bb9238d3}</destination>
		</relationship>
	</object>
	<object class="MixerBusEffectChain" id="{556d7ca2-8197-4637-a1ef-788c3ea87015}">
		<relationship name="effects">
			<destination>{695632e4-2564-40b4-8a78-92d11dc73743}</destination>
		</relationship>
	</object>
	<object class="MixerBusPanner" id="{f4feae7f-d077-4753-8463-8c35b537c117}" />
	<object class="MixerBusFader" id="{5c9de8bd-c40a-464d-8532-057ea68b2e7e}" />
	<object class="FadeCurve" id="{30ff5622-3741-4763-a787-1d63c314b251}">
		<relationship name="startPoint">
			<destination>{f062b8ff-2576-4be3-9c40-b582a53feab9}</destination>
		</relationship>
		<relationship name="endPoint">
			<destination>{d46a982f-68d9-4319-9cbf-f20edc7e5022}</destination>
		</relationship>
	</object>
	<object class="FadeCurve" id="{66da9113-c40e-4b89-b959-094559fa544c}">
		<relationship name="startPoint">
			<destination>{327920a0-4b44-4c8e-96b8-f5f66ed7935b}</destination>
		</relationship>
		<relationship name="endPoint">
			<destination>{475aa667-fadb-4bd1-bf6b-ff1c905f6867}</destination>
		</relationship>
	</object>
	<object class="MixerBusEffectChain" id="{c12fd2bd-02e0-409e-b60c-d6c1a3901557}">
		<relationship name="effects">
			<destination>{5425f132-2625-48b3-877d-4f1cae9b7ec9}</destination>
		</relationship>
	</object>
	<object class="MixerBusPanner" id="{ec452c76-ce2e-4700-a924-d551c3681a2e}" />
	<object class="MixerBusFader" id="{695632e4-2564-40b4-8a78-92d11dc73743}" />
	<object class="AutomationPoint" id="{f062b8ff-2576-4be3-9c40-b582a53feab9}">
		<property name="position">
			<value>0</value>
		</property>
		<property name="value">
			<value>0</value>
		</property>
		<property name="curveShape">
			<value>-0.2547189</value>
		</property>
	</object>
	<object class="AutomationPoint" id="{d46a982f-68d9-4319-9cbf-f20edc7e5022}">
		<property name="position">
			<value>0.10000000000000002</value>
		</property>
		<property name="value">
			<value>1</value>
		</property>
	</object>
	<object class="AutomationPoint" id="{327920a0-4b44-4c8e-96b8-f5f66ed7935b}">
		<property name="position">
			<value>0.3446822514709908</value>
		</property>
		<property name="value">
			<value>1</value>
		</property>
		<property name="curveShape">
			<value>0.25471893</value>
		</property>
	</object>
	<object class="AutomationPoint" id="{475aa667-fadb-4bd1-bf6b-ff1c905f6867}">
		<property name="position">
			<value>1.9446822514709907</value>
		</property>
		<property name="value">
			<value>0</value>
		</property>
	</object>
	<object class="MixerBusFader" id="{5425f132-2625-48b3-877d-4f1cae9b7ec9}" />
</objects>
