<?xml version="1.0" encoding="UTF-8"?>
<objects serializationModel="Studio.02.02.00">
	<object class="ParameterPreset" id="{b1c2d65f-d20b-46ed-bb7b-19c8e813db72}">
		<property name="name">
			<value>pmlyric</value>
		</property>
		<relationship name="folder">
			<destination>{ebd80d4a-6c3c-468b-883d-cc9e4f67e374}</destination>
		</relationship>
		<relationship name="parameter">
			<destination>{91ead859-b03e-4877-9522-1a8e47fddb95}</destination>
		</relationship>
	</object>
	<object class="GameParameter" id="{91ead859-b03e-4877-9522-1a8e47fddb95}">
		<property name="maximum">
			<value>14</value>
		</property>
		<property name="initialValue">
			<value>0</value>
		</property>
	</object>
</objects>
